[
    {
        "name": "file_operations",
        "members": [
            {
                "name": "read",
                "category": "fops:read",
                "user": [
                    1,
                    2,
                    3
                ]
            },
            {
                "name": "read_iter",
                "category": "fops:read_iter",
                "user": [
                    1
                ]
            },
            {
                "name": "write",
                "category": "fops:write",
                "user": [
                    1,
                    2,
                    3
                ]
            },
            {
                "name": "write_iter",
                "category": "fops:write_iter",
                "user": [
                    1
                ]
            },
            {
                "name": "unlocked_ioctl",
                "category": "fops:ioctl",
                "user": [
                    1,
                    2
                ]
            },
            {
                "name": "compat_ioctl",
                "category": "fops:ioctl_c",
                "user": [
                    1,
                    2
                ]
            },
            {
                "name": "mmap",
                "category": "fops:mmap",
                "user": [
                    1
                ]
            }
        ]
    },
    {
        "name": "fb_ops",
        "members": [
            {
                "name": "fb_read",
                "category": "fops:read",
                "user": [
                    1,
                    2,
                    3
                ]
            },
            {
                "name": "fb_write",
                "category": "fops:write",
                "user": [
                    1,
                    2,
                    3
                ]
            },
            {
                "name": "fb_ioctl",
                "category": "fops:ioctl",
                "user": [
                    1,
                    2
                ]
            },
            {
                "name": "fb_compat_ioctl",
                "category": "fops:ioctl_c",
                "user": [
                    1,
                    2
                ]
            },
            {
                "name": "fb_mmap",
                "category": "fops:mmap",
                "user": [
                    1
                ]
            }
        ]
    },
    {
        "name": "proc_ops",
        "members": [
            {
                "name": "proc_read",
                "category": "fops:read",
                "user": [
                    1,
                    2,
                    3
                ]
            },
            {
                "name": "proc_read_iter",
                "category": "fops:read_iter",
                "user": [
                    1
                ]
            },
            {
                "name": "proc_write",
                "category": "fops:write",
                "user": [
                    1,
                    2,
                    3
                ]
            },
            {
                "name": "proc_ioctl",
                "category": "fops:ioctl",
                "user": [
                    1,
                    2
                ]
            },
            {
                "name": "proc_compat_ioctl",
                "category": "fops:ioctl_c",
                "user": [
                    1,
                    2
                ]
            },
            {
                "name": "proc_mmap",
                "category": "fops:mmap",
                "user": [
                    1
                ]
            }
        ]
    },
    {
        "name": "bin_attribute",
        "members": [
            {
                "name": "read",
                "category": "fops:show",
                "user": [
                    3,
                    5,
                    4
                ]
            },
            {
                "name": "write",
                "category": "fops:store",
                "user": [
                    3,
                    5
                ]
            },
            {
                "name": "mmap",
                "category": "fops:mmap",
                "user": [
                    3
                ]
            }
        ]
    },
    {
        "name": "device_attribute",
        "members": [
            {
                "name": "show",
                "category": "fops:show",
                "user": [
                    2
                ]
            },
            {
                "name": "store",
                "category": "fops:store",
                "user": [
                    2,
                    3
                ]
            }
        ]
    },
    {
        "name": "driver_attribute",
        "members": [
            {
                "name": "show",
                "category": "fops:show",
                "user": [
                    1
                ]
            },
            {
                "name": "store",
                "category": "fops:store",
                "user": [
                    1,
                    2
                ]
            }
        ]
    },
    {
        "name": "kobj_attribute",
        "members": [
            {
                "name": "show",
                "category": "fops:show",
                "user": [
                    2
                ]
            },
            {
                "name": "store",
                "category": "fops:store",
                "user": [
                    2,
                    3
                ]
            }
        ]
    },
    {
        "name": "configfs_attribute",
        "members": [
            {
                "name": "show",
                "category": "fops:show",
                "user": [
                    1
                ]
            },
            {
                "name": "store",
                "category": "fops:store",
                "user": [
                    1,
                    2
                ]
            }
        ]
    },
    {
        "name": "class_attribute",
        "members": [
            {
                "name": "show",
                "category": "fops:show",
                "user": [
                    2
                ]
            },
            {
                "name": "store",
                "category": "fops:store",
                "user": [
                    2,
                    3
                ]
            }
        ]
    },
    {
        "name": "slab_attribute",
        "members": [
            {
                "name": "show",
                "category": "fops:show",
                "user": [
                    1
                ]
            },
            {
                "name": "store",
                "category": "fops:store",
                "user": [
                    1,
                    2
                ]
            }
        ]
    },
    {
        "name": "netdev_queue_attribute",
        "members": [
            {
                "name": "show",
                "category": "fops:show",
                "user": [
                    1
                ]
            },
            {
                "name": "store",
                "category": "fops:store",
                "user": [
                    1,
                    2
                ]
            }
        ]
    },
    {
        "name": "rx_queue_attribute",
        "members": [
            {
                "name": "show",
                "category": "fops:show",
                "user": [
                    1
                ]
            },
            {
                "name": "store",
                "category": "fops:store",
                "user": [
                    1,
                    2
                ]
            }
        ]
    },
    {
        "name": "dhd_attr",
        "members": [
            {
                "name": "show",
                "category": "fops:show"
            },
            {
                "name": "store",
                "category": "fops:store",
                "user": [
                    1,
                    2
                ]
            }
        ]
    },
    {
        "name": "f2fs_attr",
        "members": [
            {
                "name": "show",
                "category": "fops:show",
                "user": [
                    2
                ]
            },
            {
                "name": "store",
                "category": "fops:store",
                "user": [
                    2,
                    3
                ]
            }
        ]
    },
    {
        "name": "queue_sysfs_entry",
        "members": [
            {
                "name": "show",
                "category": "fops:show",
                "user": [
                    1
                ]
            },
            {
                "name": "store",
                "category": "fops:store",
                "user": [
                    1,
                    2
                ]
            }
        ]
    },
    {
        "name": "sysfs_ops",
        "members": [
            {
                "name": "show",
                "category": "fops:show",
                "user": [
                    2
                ]
            },
            {
                "name": "store",
                "category": "fops:store",
                "user": [
                    2,
                    3
                ]
            }
        ]
    },
    {
        "name": "governor_attr",
        "members": [
            {
                "name": "show",
                "category": "fops:show",
                "user": [
                    1
                ]
            },
            {
                "name": "store",
                "category": "fops:store",
                "user": [
                    1,
                    2
                ]
            }
        ]
    },
    {
        "name": "netlink_kernel_cfg",
        "members": [
            {
                "name": "input",
                "category": "netlink:netlink_entry",
                "user": [
                    0
                ]
            }
        ]
    },
    {
        "name": "genl_ops",
        "members": [
            {
                "name": "doit",
                "category": "netlink:genl_ops"
            }
        ]
    },
    {
        "name": "genl_small_ops",
        "members": [
            {
                "name": "doit",
                "category": "netlink:genl_ops"
            }
        ]
    },
    {
        "name": "wiphy_vendor_command",
        "members": [
            {
                "name": "doit",
                "category": "netlink:vendor_cmd"
            }
        ]
    },
    {
        "name": "kernel_param_ops",
        "members": [
            {
                "name": "set",
                "category": "others:kernel_param_set",
                "user": [
                    0
                ]
            },
            {
                "name": "get",
                "category": "others:kernel_param_get"
            }
        ]
    },
    {
        "name": "v4l2_subdev_core_ops",
        "members": [
            {
                "name": "ioctl",
                "category": "v4l2:v4l2_core_ioctl",
                "user": [
                    1,
                    2
                ]
            },
            {
                "name": "compat_ioctl32",
                "category": "v4l2:v4l2_core_ioctl_c",
                "user": [
                    1,
                    2
                ]
            }
        ]
    },
    {
        "name": "v4l2_ioctl_ops",
        "members": [
            {
                "name": "*",
                "category": "v4l2:v4l2_ioctl",
                "user": [
                    -1
                ]
            }
        ]
    },
    {
        "name": "power_supply_desc",
        "members": [
            {
                "name": "get_property",
                "category": "others:power_property_get"
            },
            {
                "name": "set_property",
                "category": "others:power_property_set",
                "user": [
                    2
                ]
            }
        ]
    },
    {
        "name": "qcom_bwmon_attr",
        "members": [
            {
                "name": "show",
                "category": "fops:show",
                "user": [
                    2
                ]
            },
            {
                "name": "store",
                "category": "fops:store",
                "user": [
                    2,
                    3
                ]
            }
        ]
    },
    {
        "name": "elv_fs_entry",
        "members": [
            {
                "name": "show",
                "category": "fops:show",
                "user": [
                    1
                ]
            },
            {
                "name": "store",
                "category": "fops:store",
                "user": [
                    1,
                    2
                ]
            }
        ]
    },
    {
        "name": "kgsl_gpu_sysfs_attr",
        "members": [
            {
                "name": "show",
                "category": "fops:show",
                "user": [
                    1
                ]
            },
            {
                "name": "store",
                "category": "fops:store",
                "user": [
                    1,
                    2
                ]
            }
        ]
    },
    {
        "name": "cftype",
        "members": [
            {
                "name": "seq_show",
                "category": "fops:seq_show"
            },
            {
                "name": "write_u64",
                "category": "fops:write_one",
                "user": [
                    2
                ]
            },
            {
                "name": "write_s64",
                "category": "fops:write_one",
                "user": [
                    2
                ]
            }
        ]
    },
    {
        "name": "tty_operations",
        "members": [
            {
                "name": "ioctl",
                "category": "fops:ioctl",
                "user": [
                    1,
                    2
                ]
            },
            {
                "name": "compat_ioctl",
                "category": "fops:ioctl_c",
                "user": [
                    1,
                    2
                ]
            },
            {
                "name": "proc_show",
                "category": "fops:seq_show"
            }
        ]
    },
    {
        "name": "seq_operations",
        "members": [
            {
                "name": "show",
                "category": "fops:seq_show"
            }
        ]
    },
    {
        "name": "proto_ops",
        "members": [
            {
                "name": "mmap",
                "category": "fops:mmap",
                "user": [
                    2
                ]
            },
            {
                "name": "ioctl",
                "category": "fops:ioctl_c",
                "user": [
                    1,
                    2
                ]
            }
        ]
    },
    {
        "name": "iio_ioctl_handler",
        "members": [
            {
                "name": "ioctl",
                "category": "fops:ioctl",
                "user": [
                    2,
                    3
                ]
            }
        ]
    },
    {
        "name": "media_file_operations",
        "members": [
            {
                "name": "ioctl",
                "category": "fops:ioctl",
                "user": [
                    1,
                    2
                ]
            },
            {
                "name": "compat_ioctl",
                "category": "fops:ioctl_c",
                "user": [
                    1,
                    2
                ]
            }
        ]
    },
    {
        "name": "address_space_operations",
        "members": [
            {
                "name": "direct_IO",
                "category": "fops:seq_write"
            }
        ]
    },
    {
        "name": "v4l2_file_operations",
        "members": [
            {
                "name": "mmap",
                "category": "fops:mmap",
                "user": [
                    1
                ]
            },
            {
                "name": "compat_ioctl32",
                "category": "fops:ioctl_c",
                "user": [
                    1,
                    2
                ]
            },
            {
                "name": "read",
                "category": "fops:read",
                "user": [
                    1,
                    2,
                    3
                ]
            },
            {
                "name": "unlocked_ioctl",
                "category": "fops:ioctl",
                "user": [
                    1,
                    2
                ]
            },
            {
                "name": "write",
                "category": "fops:write",
                "user": [
                    1,
                    2,
                    3
                ]
            }
        ]
    },
    {
        "name": "hid_ll_driver",
        "members": [
            {
                "name": "raw_request",
                "category": "others:hid_raw_request",
                "user": [
                    2,
                    3
                ]
            },
            {
                "name": "output_report",
                "category": "others:hid_output_report",
                "user": [
                    1,
                    2
                ]
            }
        ]
    },
    {
        "name": "va_md_attribute",
        "members": [
            {
                "name": "show",
                "category": "fops:show",
                "user": [
                    2
                ]
            },
            {
                "name": "store",
                "category": "fops:store",
                "user": [
                    2,
                    3
                ]
            }
        ]
    },
    {
        "name": "qcom_memlat_attr",
        "members": [
            {
                "name": "show",
                "category": "fops:show",
                "user": [
                    2
                ]
            },
            {
                "name": "store",
                "category": "fops:store",
                "user": [
                    2,
                    3
                ]
            }
        ]
    },
    {
        "name": "snd_info_entry_ops",
        "members": [
            {
                "name": "mmap",
                "category": "fops:mmap",
                "user": [
                    4
                ]
            },
            {
                "name": "ioctl",
                "category": "fops:ioctl",
                "user": [
                    3,
                    4
                ]
            }
        ]
    },
    {
        "name": "dm_sysfs_attr",
        "members": [
            {
                "name": "show",
                "category": "fops:show",
                "user": [
                    1
                ]
            },
            {
                "name": "store",
                "category": "fops:store",
                "user": [
                    1,
                    2
                ]
            }
        ]
    },
    {
        "name": "reset_attribute",
        "members": [
            {
                "name": "show",
                "category": "fops:show",
                "user": [
                    2
                ]
            },
            {
                "name": "store",
                "category": "fops:store",
                "user": [
                    2,
                    3
                ]
            }
        ]
    },
    {
        "name": "qcom_pmu_attr",
        "members": [
            {
                "name": "show",
                "category": "fops:show",
                "user": [
                    2
                ]
            },
            {
                "name": "store",
                "category": "fops:store",
                "user": [
                    2,
                    3
                ]
            }
        ]
    },
    {
        "name": "drm_info_list",
        "members": [
            {
                "name": "show",
                "category": "fops:seq_show"
            }
        ]
    },
    {
        "name": "l2tp_session",
        "members": [
            {
                "name": "show",
                "category": "fops:show"
            }
        ]
    },
    {
        "name": "xhci_file_map",
        "members": [
            {
                "name": "show",
                "category": "fops:seq_show"
            }
        ]
    },
    {
        "name": "uart_ops",
        "members": [
            {
                "name": "ioctl",
                "category": "fops:ioctl",
                "user": [
                    1,
                    2
                ]
            }
        ]
    },
    {
        "name": "block_device_operations",
        "members": [
            {
                "name": "ioctl",
                "category": "fops:ioctl",
                "user": [
                    2,
                    3
                ]
            },
            {
                "name": "compat_ioctl",
                "category": "fops:ioctl_c",
                "user": [
                    2,
                    3
                ]
            }
        ]
    },
    {
        "name": "tty_ldisc_ops",
        "members": [
            {
                "name": "ioctl",
                "category": "fops:ioctl",
                "user": [
                    1,
                    2
                ]
            },
            {
                "name": "compat_ioctl",
                "category": "fops:ioctl_c",
                "user": [
                    1,
                    2
                ]
            }
        ]
    },
    {
        "name": "bpf_map_ops",
        "members": [
            {
                "name": "map_mmap",
                "category": "fops:mmap",
                "user": [
                    1
                ]
            }
        ]
    },
    {
        "name": "freq_attr",
        "members": [
            {
                "name": "show",
                "category": "fops:show",
                "user": [
                    1
                ]
            },
            {
                "name": "store",
                "category": "fops:store",
                "user": [
                    1,
                    2
                ]
            }
        ]
    },
    {
        "name": "kgsl_snapshot_attribute",
        "members": [
            {
                "name": "show",
                "category": "fops:show",
                "user": [
                    1
                ]
            },
            {
                "name": "store",
                "category": "fops:store",
                "user": [
                    1,
                    2
                ]
            }
        ]
    },
    {
        "name": "bus_attribute",
        "members": [
            {
                "name": "show",
                "category": "fops:show",
                "user": [
                    1
                ]
            },
            {
                "name": "store",
                "category": "fops:store",
                "user": [
                    1,
                    2
                ]
            }
        ]
    },
    {
        "name": "cpuidle_state_attr",
        "members": [
            {
                "name": "show",
                "category": "fops:show",
                "user": [
                    2
                ]
            },
            {
                "name": "store",
                "category": "fops:store",
                "user": [
                    2,
                    3
                ]
            }
        ]
    },
    {
        "name": "edac_pci_dev_attribute",
        "members": [
            {
                "name": "show",
                "category": "fops:show",
                "user": [
                    1
                ]
            },
            {
                "name": "store",
                "category": "fops:store",
                "user": [
                    1,
                    2
                ]
            }
        ]
    },
    {
        "name": "core_ctl_attr",
        "members": [
            {
                "name": "show",
                "category": "fops:show",
                "user": [
                    1
                ]
            },
            {
                "name": "store",
                "category": "fops:store",
                "user": [
                    1,
                    2
                ]
            }
        ]
    },
    {
        "name": "ppp_channel_ops",
        "members": [
            {
                "name": "ioctl",
                "category": "fops:ioctl",
                "user": [
                    1,
                    2
                ]
            }
        ]
    },
    {
        "name": "posix_clock_operations",
        "members": [
            {
                "name": "ioctl",
                "category": "fops:ioctl",
                "user": [
                    1,
                    2
                ]
            },
            {
                "name": "read",
                "category": "fops:read",
                "user": [
                    2,
                    3
                ]
            }
        ]
    },
    {
        "name": "ctl_info_attribute",
        "members": [
            {
                "name": "show",
                "category": "fops:show",
                "user": [
                    1
                ]
            },
            {
                "name": "store",
                "category": "fops:store",
                "user": [
                    1,
                    2
                ]
            }
        ]
    },
    {
        "name": "dispatcher_attribute",
        "members": [
            {
                "name": "show",
                "category": "fops:show",
                "user": [
                    2
                ]
            },
            {
                "name": "store",
                "category": "fops:store",
                "user": [
                    2,
                    3
                ]
            }
        ]
    },
    {
        "name": "snd_compress_ops",
        "members": [
            {
                "name": "mmap",
                "category": "fops:mmap",
                "user": [
                    2
                ]
            }
        ]
    },
    {
        "name": "pppox_proto",
        "members": [
            {
                "name": "ioctl",
                "category": "fops:ioctl",
                "user": [
                    1,
                    2
                ]
            }
        ]
    },
    {
        "name": "iommu_group_attribute",
        "members": [
            {
                "name": "show",
                "category": "fops:show",
                "user": [
                    1
                ]
            },
            {
                "name": "store",
                "category": "fops:store",
                "user": [
                    1,
                    2
                ]
            }
        ]
    },
    {
        "name": "qcom_c1dcvs_attr",
        "members": [
            {
                "name": "show",
                "category": "fops:show"
            },
            {
                "name": "store",
                "category": "fops:store",
                "user": [
                    1,
                    2
                ]
            }
        ]
    },
    {
        "name": "qcom_dynpf_attr",
        "members": [
            {
                "name": "show",
                "category": "fops:show"
            },
            {
                "name": "store",
                "category": "fops:store",
                "user": [
                    1,
                    2
                ]
            }
        ]
    },
    {
        "name": "qcom_dcvs_attr",
        "members": [
            {
                "name": "show",
                "category": "fops:show",
                "user": [
                    2
                ]
            },
            {
                "name": "store",
                "category": "fops:store",
                "user": [
                    2,
                    3
                ]
            }
        ]
    },
    {
        "name": "core_hang_attribute",
        "members": [
            {
                "name": "show",
                "category": "fops:show"
            },
            {
                "name": "store",
                "category": "fops:store",
                "user": [
                    1,
                    2
                ]
            }
        ]
    },
    {
        "name": "blk_mq_debugfs_attr",
        "members": [
            {
                "name": "show",
                "category": "fops:seq_show"
            },
            {
                "name": "write",
                "category": "fops:write",
                "user": [
                    1,
                    2
                ]
            }
        ]
    },
    {
        "name": "security_list_options",
        "members": [
            {
                "name": "*",
                "category": "others:sec_hooks"
            }
        ]
    },
    {
        "name": "mtk_swpm_sysfs_op",
        "members": [
            {
                "name": "fs_read",
                "category": "fops:read",
                "user": [
                    1
                ]
            },
            {
                "name": "fs_write",
                "category": "fops:write",
                "user": [
                    0,
                    1
                ]
            }
        ]
    },
    {
        "name": "wmt_platform_dbg_bridge",
        "members": [
            {
                "name": "read_cb",
                "category": "fops:read",
                "user": [
                    1,
                    2
                ]
            },
            {
                "name": "write_cb",
                "category": "fops:write",
                "user": [
                    1,
                    2
                ]
            }
        ]
    },
    {
        "name": "mtk_lp_sysfs_op",
        "members": [
            {
                "name": "fs_read",
                "category": "fops:read",
                "user": [
                    1
                ]
            },
            {
                "name": "fs_write",
                "category": "fops:write",
                "user": [
                    0,
                    1
                ]
            }
        ]
    },
    {
        "name": "ccci_attribute",
        "members": [
            {
                "name": "show",
                "category": "fops:show"
            },
            {
                "name": "store",
                "category": "fops:store",
                "user": [
                    0,
                    1
                ]
            }
        ]
    },
    {
        "name": "stAF_DrvList",
        "members": [
            {
                "name": "pAF_Ioctl",
                "category": "fops:ioctl",
                "user": [
                    1,
                    2
                ]
            }
        ]
    },
    {
        "name": "iio_buffer_access_funcs",
        "members": [
            {
                "name": "read",
                "category": "fops:read",
                "user": [
                    2,
                    1
                ]
            },
            {
                "name": "write",
                "category": "fops:write",
                "user": [
                    1,
                    2
                ]
            }
        ]
    },
    {
        "name": "flashlight_operations",
        "members": [
            {
                "name": "flashlight_ioctl",
                "category": "fops:ioctl",
                "user": [
                    0,
                    1
                ]
            }
        ]
    },
    {
        "name": "proto",
        "members": [
            {
                "name": "compat_ioctl",
                "category": "fops:ioctl_c",
                "user": [
                    1,
                    2
                ]
            }
        ]
    },
    {
        "name": "conn_adaptor_drv_gen_cb",
        "members": [
            {
                "name": "coredump_emi_read",
                "category": "fops:read",
                "user": [
                    1,
                    2
                ]
            }
        ]
    },
    {
        "name": "cmd_fn",
        "members": [
            {
                "name": "fn",
                "category": "fops:seq_show",
                "user": [
                    0,
                    1
                ]
            },
            {
                "name": "fn",
                "category": "fops:seq_write",
                "user": [
                    0,
                    1
                ]
            }
        ]
    },
    {
        "name": "hif_hook_ptr",
        "members": [
            {
                "name": "log_read_to_user",
                "category": "fops:read",
                "user": [
                    0,
                    1
                ]
            }
        ]
    },
    {
        "name": "mtk_btag_vops",
        "members": [
            {
                "name": "seq_show",
                "category": "fops:seq_show"
            },
            {
                "name": "sub_write",
                "category": "fops:write",
                "user": [
                    0,
                    1
                ]
            }
        ]
    },
    {
        "name": "goodix_ext_attribute",
        "members": [
            {
                "name": "show",
                "category": "fops:show",
                "user": [
                    1
                ]
            },
            {
                "name": "store",
                "category": "fops:store",
                "user": [
                    1,
                    2
                ]
            }
        ]
    }
]